{
  "id": "wenbing-13-30",
  "title": "温病条辨 湿温 第 30 节 · 八三、脉左弦，暮热早凉，",
  "content": "八三、脉左弦，暮热早凉，汗解渴饮，少阳疟偏于热重者，青蒿鳖甲汤主之。 少阳切近三阴，立法以一面领邪外出，一面防邪内入为要领。小柴胡汤以柴胡领邪，以人参、大 枣、甘草护正；以柴胡清表热，以黄芩、甘草苦甘清里热∶半夏、生姜两和肝胃，蠲内饮，宣胃阳，降胃 阴，疏肝，用生姜大枣调和营卫。使表者不争，里者内安，清者清，补者补，升者升，降者降，平者平， 故曰和也。青蒿鳖甲汤，用小柴胡法而小变之，却不用小柴胡之药者，小柴胡原为伤寒立方，疟缘于 暑湿，其受邪之源，本自不同，故必变通其药味，以同在少阳一经，故不能离其法。青蒿鳖甲汤以青 蒿领邪，青蒿较柴胡力软，且芳香逐秽，开络之功，则较柴胡有独胜。寒邪伤阳，柴胡汤中之人参、甘 草、生姜，皆护阳者也；暑热伤阴，故改用鳖甲护阴，鳖甲乃蠕动之物，且能入阴络搜邪。柴胡汤以 胁痛、干呕为饮邪所致，故以姜、半通阳降阴而清饮邪；青蒿鳖甲汤以邪热伤阴，则用知母、花粉以 清热邪而止渴，丹皮清少阳血分，桑叶清少阳络中气分。宗古法而变古方者，以邪之偏寒偏热不同 也，此叶氏之读古书，善用古方，岂他人之死于句下者，所可同日语哉！",
  "translation": "",
  "keywords": []
}
