{
  "id": "wenbing-03-03",
  "title": "温病条辨 风温、温热、温疫、温毒、冬温 第 3 节 · 三、太阴之为病，脉不缓不",
  "content": "三、太阴之为病，脉不缓不紧而动数，或两寸独大，尺肤热，头痛，微恶风寒，身热自汗，口渴，或 不渴，而咳，午后热甚者，名曰温病。 不缓，则非太阳中风矣；不紧，则非太阳伤寒矣；动数者，风火相煽之象，经谓之燥；两寸独大， 火克金也。尺肤热，尺部肌肤热甚，火反克水也。头痛、恶风寒、身热自汗、与太阳中风无异，此处最 足以相混，于何辨之？于脉动数，不缓不紧，证有或渴、或咳、尺热、午后热甚辨之。太阳头痛，风寒之 邪，循太阳经上至头与项，而项强头痛也。太阴之 头痛，肺生天气，天气郁，则头亦痛也，且春气在头，又火炎上也。吴又可谓浮泛太阳经者，臆说 也。伤寒之恶寒，太阳属寒水而主表，故恶风寒、温病之恶寒，肺合皮毛而亦主表，故亦恶风寒 也。太阳病则周身之阳气郁，故身热；肺主化气，肺病不能化气，气郁则身亦热也。太阳自汗，风疏 卫也；太阴自汗，皮毛开也，肺亦主卫。渴，火克金也。咳，肺气郁也。午后热甚，浊邪归下，又火旺 时也，又阴受火克之象也。",
  "translation": "",
  "keywords": []
}
